friendlywords/__init__.py
friendlywords/collections.txt
friendlywords/objects.txt
friendlywords/predicates.txt
friendlywords/teams.txt
friendlywords/words/collections.txt
friendlywords/words/objects.txt
friendlywords/words/predicates.txt
friendlywords/words/teams.txt
friendlywords/words/world.txt
py_friendlywords-1.2.0.post2.dist-info/LICENSE.md
py_friendlywords-1.2.0.post2.dist-info/METADATA
py_friendlywords-1.2.0.post2.dist-info/WHEEL
py_friendlywords-1.2.0.post2.dist-info/top_level.txt
py_friendlywords-1.2.0.post2.dist-info/RECORD
