Metadata-Version: 2.1
Name: py-friendlywords
Version: 1.2.0.post2
Summary: Curated lists of friendly words, as used in project names and elsewhere on glitch.com
Home-page: https://github.com/betatim/python-friendlywords
Author: Tim Head
License: UNKNOWN
Platform: UNKNOWN
Requires-Python: >=3.7
License-File: LICENSE.md
